beholder.py
beholder-0.0.0.dist-info/LICENSE.md
beholder-0.0.0.dist-info/WHEEL
beholder-0.0.0.dist-info/METADATA
beholder-0.0.0.dist-info/RECORD
